prefigure/__init__.py
prefigure/ofc.py
prefigure/prefigure.py
prefigure-0.0.10.dist-info/LICENSE.txt
prefigure-0.0.10.dist-info/METADATA
prefigure-0.0.10.dist-info/WHEEL
prefigure-0.0.10.dist-info/top_level.txt
prefigure-0.0.10.dist-info/RECORD
