Metadata-Version: 2.1
Name: prefigure
Version: 0.0.10
Summary: Run configuration management utils: combines configparser, argparse, and wandb.API
Home-page: https://github.com/drscotthawley/prefigure
Author: Scott H. Hawley
Author-email: scott.hawley@belmont.edu
License: MIT
Platform: UNKNOWN
Classifier: Development Status :: 1 - Planning
Classifier: Intended Audience :: Science/Research
Classifier: License :: OSI Approved :: MIT License
Classifier: Operating System :: POSIX :: Linux
Classifier: Programming Language :: Python :: 3.7
Classifier: Programming Language :: Python :: 3.8
Classifier: Programming Language :: Python :: 3.9
Classifier: Programming Language :: Python :: 3.10
License-File: LICENSE.txt
Requires-Dist: argparse
Requires-Dist: configparser
Requires-Dist: gin-config
Requires-Dist: gradio
Requires-Dist: pytorch-lightning
Requires-Dist: wandb
